easekit/__init__.py
easekit/scorer.py
easekit/sentiment.py
easekit/similarity.py
easekit/utils.py
easekit-1.0.0.dist-info/METADATA
easekit-1.0.0.dist-info/WHEEL
easekit-1.0.0.dist-info/top_level.txt
easekit-1.0.0.dist-info/RECORD
