Metadata-Version: 2.4
Name: easekit
Version: 1.0.0
Summary: A metric to evaluate empathy in dialogue systems
Home-page: https://github.com/srishtigupta253/easekit
Author: Srishti Gupta
Author-email: srishtig253@gmail.com
Classifier: Programming Language :: Python :: 3
Classifier: License :: OSI Approved :: MIT License
Classifier: Operating System :: OS Independent
Requires-Python: >=3.7
Requires-Dist: numpy
Requires-Dist: torch
Requires-Dist: transformers
Requires-Dist: scikit-learn
Requires-Dist: nltk
Requires-Dist: vaderSentiment
Dynamic: author
Dynamic: author-email
Dynamic: classifier
Dynamic: description
Dynamic: description-content-type
Dynamic: home-page
Dynamic: requires-dist
Dynamic: requires-python
Dynamic: summary
